DESCRIPTION.rst
LICENSE
MANIFEST.in
README.md
setup.py
sandstone/__init__.py
sandstone/app.py
sandstone/global_settings.py
sandstone/urls.py
sandstone.egg-info/PKG-INFO
sandstone.egg-info/SOURCES.txt
sandstone.egg-info/dependency_links.txt
sandstone.egg-info/entry_points.txt
sandstone.egg-info/not-zip-safe
sandstone.egg-info/requires.txt
sandstone.egg-info/top_level.txt
sandstone/apps/__init__.py
sandstone/apps/codeeditor/__init__.py
sandstone/apps/codeeditor/settings.py
sandstone/apps/codeeditor/static/ace.controller.js
sandstone/apps/codeeditor/static/editor.css
sandstone/apps/codeeditor/static/editor.html
sandstone/apps/codeeditor/static/editor.js
sandstone/apps/codeeditor/static/editor.service.js
sandstone/apps/codeeditor/static/filetree.controller.js
sandstone/apps/codeeditor/static/settings.controller.js
sandstone/apps/codeeditor/static/tabs.controller.js
sandstone/apps/codeeditor/static/templates/ace.html
sandstone/apps/codeeditor/static/templates/close-unsaved-modal.html
sandstone/apps/codeeditor/static/templates/create-modal.html
sandstone/apps/codeeditor/static/templates/delete-modal.html
sandstone/apps/codeeditor/static/templates/file-changed-modal.html
sandstone/apps/codeeditor/static/templates/filetree-controls.html
sandstone/apps/codeeditor/static/templates/filetree.html
sandstone/apps/codeeditor/static/templates/rename-modal.html
sandstone/apps/codeeditor/static/templates/saveas-modal.html
sandstone/apps/codeeditor/static/templates/settings.html
sandstone/apps/codeeditor/static/templates/tabs.html
sandstone/apps/codeeditor/tests/e2e/editor.spec.js
sandstone/apps/codeeditor/tests/e2e/filetree.spec.js
sandstone/apps/codeeditor/tests/e2e/routing.spec.js
sandstone/apps/codeeditor/tests/js/editor.service.spec.js
sandstone/apps/codeeditor/tests/js/editortabs.controller.spec.js
sandstone/apps/codeeditor/tests/js/filetree.controller.spec.js
sandstone/apps/codeeditor/tests/js/settings.controller.spec.js
sandstone/apps/filebrowser/__init__.py
sandstone/apps/filebrowser/handlers.py
sandstone/apps/filebrowser/settings.py
sandstone/apps/filebrowser/urls.py
sandstone/apps/filebrowser/static/createmodal.controller.js
sandstone/apps/filebrowser/static/deletemodal.controller.js
